{
  "finding_name": "Loop Recorder",
  "description": "A loop recorder is a small device that is implanted under the skin to monitor and record the electrical activity of the heart.",
  "attributes": [
    {
      "name": "Presence of Loop Recorder",
      "description": "Indicates whether a loop recorder is present or not",
      "type": "choice",
      "values": [
        {
          "name": "Present",
          "description": "A loop recorder is present"
        },
        {
          "name": "Absent",
          "description": "A loop recorder is absent"
        }
      ],
      "required": true
    },
    {
      "name": "Side",
      "description": "Indicates the side where the loop recorder is located",
      "type": "choice",
      "values": [
        {
          "name": "Left",
          "description": "The loop recorder is located on the left side"
        },
        {
          "name": "Right",
          "description": "The loop recorder is located on the right side"
        }
      ],
      "required": true
    },
    {
      "name": "Location",
      "description": "Indicates the location of the loop recorder",
      "type": "choice",
      "values": [
        {
          "name": "Pre-pectoral",
          "description": "The loop recorder is located in the pre-pectoral region"
        },
        {
          "name": "Subcutaneous",
          "description": "The loop recorder is located subcutaneously"
        },
        {
          "name": "Other",
          "description": "The loop recorder is located in another location"
        }
      ],
      "required": true
    }
  ]
}