{
  "finding_name": "Morgagni Hernia",
  "description": "A hernia that occurs in the anterior portion of the diaphragm, specifically in the area of the Morgagni foramen.",
  "attributes": [
    {
      "name": "Presence of Morgagni Hernia",
      "description": "Whether a Morgagni Hernia is present or not",
      "type": "choice",
      "values": [
        {
          "name": "Yes",
          "description": "Morgagni Hernia is present"
        },
        {
          "name": "No",
          "description": "Morgagni Hernia is absent"
        }
      ],
      "required": true
    },
    {
      "name": "Side",
      "description": "The side of the Morgagni Hernia",
      "type": "choice",
      "values": [
        {
          "name": "Left",
          "description": "Morgagni Hernia is on the left side"
        },
        {
          "name": "Right",
          "description": "Morgagni Hernia is on the right side"
        },
        {
          "name": "Bilateral",
          "description": "Morgagni Hernia is on both sides"
        }
      ],
      "required": true
    },
    {
      "name": "Size",
      "description": "The size of the Morgagni Hernia",
      "type": "choice",
      "values": [
        {
          "name": "Small",
          "description": "Morgagni Hernia is small in size"
        },
        {
          "name": "Medium",
          "description": "Morgagni Hernia is medium in size"
        },
        {
          "name": "Large",
          "description": "Morgagni Hernia is large in size"
        }
      ],
      "required": true
    },
    {
      "name": "Contents",
      "description": "The contents of the Morgagni Hernia",
      "type": "choice",
      "values": [
        {
          "name": "Fat",
          "description": "Morgagni Hernia contains fat"
        },
        {
          "name": "Bowel",
          "description": "Morgagni Hernia contains bowel"
        },
        {
          "name": "Both",
          "description": "Morgagni Hernia contains both fat and bowel"
        },
        {
          "name": "Other",
          "description": "Morgagni Hernia contains other contents"
        }
      ],
      "required": true
    },
    {
      "name": "Cardiac or Mediastinal Displacement",
      "description": "Whether there is associated cardiac or mediastinal displacement",
      "type": "choice",
      "values": [
        {
          "name": "Present",
          "description": "Associated cardiac or mediastinal displacement is present"
        },
        {
          "name": "Absent",
          "description": "Associated cardiac or mediastinal displacement is absent"
        }
      ],
      "required": true
    },
    {
      "name": "Other Diaphragmatic Hernias",
      "description": "Whether there are other diaphragmatic hernias present",
      "type": "choice",
      "values": [
        {
          "name": "Present",
          "description": "Other diaphragmatic hernias are present"
        },
        {
          "name": "Absent",
          "description": "Other diaphragmatic hernias are absent"
        }
      ],
      "required": true
    }
  ]
}